imgetr/__init__.py
imgetr/imgetr.py
imgetr-1.0.0.dist-info/LICENSE
imgetr-1.0.0.dist-info/METADATA
imgetr-1.0.0.dist-info/WHEEL
imgetr-1.0.0.dist-info/entry_points.txt
imgetr-1.0.0.dist-info/top_level.txt
imgetr-1.0.0.dist-info/RECORD
