Metadata-Version: 2.1
Name: imgetr
Version: 1.0.0
Summary: Command line tool for downloading images from web page.
Home-page: https://github.com/brancisco/imgetr
Author: Brandon Aguirre
Author-email: branciscodigital@gmail.com
License: GNU GENERAL PUBLIC LICENSE
Keywords: command line scrape python package imgetr img image download
Platform: UNKNOWN
Classifier: Programming Language :: Python :: 3
Classifier: License :: OSI Approved :: MIT License
Classifier: Operating System :: OS Independent
License-File: LICENSE
Requires-Dist: beautifulsoup4 (==4.10.0)
Requires-Dist: certifi (==2021.10.8)
Requires-Dist: charset-normalizer (==2.0.7)
Requires-Dist: idna (==3.3)
Requires-Dist: requests (==2.26.0)
Requires-Dist: soupsieve (==2.2.1)
Requires-Dist: urllib3 (==1.26.7)
